{

    "coc.preferences.snippets.enable": false,
    "coc.preferences.useQuickfixForLocations": true,

    "coc.source.buffer.enable": false,
    "coc.source.file.ignoreHidden": false,

    "codeLens.enable": true,
    "diagnostic.enable": false,
    "signature.enable": false,

    "python.analysis.diagnosticEnabled": false,
    "python.autoComplete.addBrackets": true,
    "python.autoComplete.showAdvancedMembers": false,
    "python.jediEnabled": true,
    "python.linting.enabled": false,
    "python.workspaceSymbols.enabled": false,

    "suggest.floatEnable": false,
    "suggest.noselect": false,
    "suggest.removeDuplicateItems": true,
    "suggest.snippetIndicator": ""

}
